qg_eureka/__init__.py
qg_eureka/client.py
qg_eureka/exc.py
qg_eureka/log.py
qg_eureka-0.0.1.dist-info/METADATA
qg_eureka-0.0.1.dist-info/WHEEL
qg_eureka-0.0.1.dist-info/top_level.txt
qg_eureka-0.0.1.dist-info/RECORD
